{
  "type": "File",
  "start": 0,
  "end": 422,
  "loc": {
    "start": {
      "line": 1,
      "column": 0
    },
    "end": {
      "line": 15,
      "column": 33
    }
  },
  "program": {
    "type": "Program",
    "start": 0,
    "end": 422,
    "loc": {
      "start": {
        "line": 1,
        "column": 0
      },
      "end": {
        "line": 15,
        "column": 33
      }
    },
    "sourceType": "module",
    "body": [
      {
        "type": "FunctionDeclaration",
        "start": 129,
        "end": 387,
        "loc": {
          "start": {
            "line": 4,
            "column": 0
          },
          "end": {
            "line": 13,
            "column": 1
          }
        },
        "id": {
          "type": "Identifier",
          "start": 138,
          "end": 151,
          "loc": {
            "start": {
              "line": 4,
              "column": 9
            },
            "end": {
              "line": 4,
              "column": 22
            },
            "identifierName": "StringReverse"
          },
          "name": "StringReverse",
          "leadingComments": null
        },
        "generator": false,
        "expression": false,
        "async": false,
        "params": [
          {
            "type": "Identifier",
            "start": 152,
            "end": 156,
            "loc": {
              "start": {
                "line": 4,
                "column": 23
              },
              "end": {
                "line": 4,
                "column": 27
              },
              "identifierName": "data"
            },
            "name": "data"
          }
        ],
        "body": {
          "type": "BlockStatement",
          "start": 157,
          "end": 387,
          "loc": {
            "start": {
              "line": 4,
              "column": 28
            },
            "end": {
              "line": 13,
              "column": 1
            }
          },
          "body": [
            {
              "type": "VariableDeclaration",
              "start": 161,
              "end": 176,
              "loc": {
                "start": {
                  "line": 5,
                  "column": 2
                },
                "end": {
                  "line": 5,
                  "column": 17
                }
              },
              "declarations": [
                {
                  "type": "VariableDeclarator",
                  "start": 165,
                  "end": 175,
                  "loc": {
                    "start": {
                      "line": 5,
                      "column": 6
                    },
                    "end": {
                      "line": 5,
                      "column": 16
                    }
                  },
                  "id": {
                    "type": "Identifier",
                    "start": 165,
                    "end": 172,
                    "loc": {
                      "start": {
                        "line": 5,
                        "column": 6
                      },
                      "end": {
                        "line": 5,
                        "column": 13
                      },
                      "identifierName": "reverse"
                    },
                    "name": "reverse"
                  },
                  "init": {
                    "type": "StringLiteral",
                    "start": 173,
                    "end": 175,
                    "loc": {
                      "start": {
                        "line": 5,
                        "column": 14
                      },
                      "end": {
                        "line": 5,
                        "column": 16
                      }
                    },
                    "extra": {
                      "rawValue": "",
                      "raw": "\"\""
                    },
                    "value": ""
                  }
                }
              ],
              "kind": "let"
            },
            {
              "type": "ForStatement",
              "start": 179,
              "end": 312,
              "loc": {
                "start": {
                  "line": 6,
                  "column": 2
                },
                "end": {
                  "line": 8,
                  "column": 3
                }
              },
              "init": {
                "type": "VariableDeclaration",
                "start": 183,
                "end": 204,
                "loc": {
                  "start": {
                    "line": 6,
                    "column": 6
                  },
                  "end": {
                    "line": 6,
                    "column": 27
                  }
                },
                "declarations": [
                  {
                    "type": "VariableDeclarator",
                    "start": 187,
                    "end": 204,
                    "loc": {
                      "start": {
                        "line": 6,
                        "column": 10
                      },
                      "end": {
                        "line": 6,
                        "column": 27
                      }
                    },
                    "id": {
                      "type": "Identifier",
                      "start": 187,
                      "end": 188,
                      "loc": {
                        "start": {
                          "line": 6,
                          "column": 10
                        },
                        "end": {
                          "line": 6,
                          "column": 11
                        },
                        "identifierName": "i"
                      },
                      "name": "i"
                    },
                    "init": {
                      "type": "BinaryExpression",
                      "start": 191,
                      "end": 204,
                      "loc": {
                        "start": {
                          "line": 6,
                          "column": 14
                        },
                        "end": {
                          "line": 6,
                          "column": 27
                        }
                      },
                      "left": {
                        "type": "MemberExpression",
                        "start": 191,
                        "end": 202,
                        "loc": {
                          "start": {
                            "line": 6,
                            "column": 14
                          },
                          "end": {
                            "line": 6,
                            "column": 25
                          }
                        },
                        "object": {
                          "type": "Identifier",
                          "start": 191,
                          "end": 195,
                          "loc": {
                            "start": {
                              "line": 6,
                              "column": 14
                            },
                            "end": {
                              "line": 6,
                              "column": 18
                            },
                            "identifierName": "data"
                          },
                          "name": "data"
                        },
                        "property": {
                          "type": "Identifier",
                          "start": 196,
                          "end": 202,
                          "loc": {
                            "start": {
                              "line": 6,
                              "column": 19
                            },
                            "end": {
                              "line": 6,
                              "column": 25
                            },
                            "identifierName": "length"
                          },
                          "name": "length"
                        },
                        "computed": false
                      },
                      "operator": "-",
                      "right": {
                        "type": "NumericLiteral",
                        "start": 203,
                        "end": 204,
                        "loc": {
                          "start": {
                            "line": 6,
                            "column": 26
                          },
                          "end": {
                            "line": 6,
                            "column": 27
                          }
                        },
                        "extra": {
                          "rawValue": 1,
                          "raw": "1"
                        },
                        "value": 1
                      }
                    }
                  }
                ],
                "kind": "var"
              },
              "test": {
                "type": "BinaryExpression",
                "start": 206,
                "end": 210,
                "loc": {
                  "start": {
                    "line": 6,
                    "column": 29
                  },
                  "end": {
                    "line": 6,
                    "column": 33
                  }
                },
                "left": {
                  "type": "Identifier",
                  "start": 206,
                  "end": 207,
                  "loc": {
                    "start": {
                      "line": 6,
                      "column": 29
                    },
                    "end": {
                      "line": 6,
                      "column": 30
                    },
                    "identifierName": "i"
                  },
                  "name": "i"
                },
                "operator": ">=",
                "right": {
                  "type": "NumericLiteral",
                  "start": 209,
                  "end": 210,
                  "loc": {
                    "start": {
                      "line": 6,
                      "column": 32
                    },
                    "end": {
                      "line": 6,
                      "column": 33
                    }
                  },
                  "extra": {
                    "rawValue": 0,
                    "raw": "0"
                  },
                  "value": 0
                }
              },
              "update": {
                "type": "UpdateExpression",
                "start": 212,
                "end": 215,
                "loc": {
                  "start": {
                    "line": 6,
                    "column": 35
                  },
                  "end": {
                    "line": 6,
                    "column": 38
                  }
                },
                "operator": "--",
                "prefix": false,
                "argument": {
                  "type": "Identifier",
                  "start": 212,
                  "end": 213,
                  "loc": {
                    "start": {
                      "line": 6,
                      "column": 35
                    },
                    "end": {
                      "line": 6,
                      "column": 36
                    },
                    "identifierName": "i"
                  },
                  "name": "i"
                }
              },
              "body": {
                "type": "BlockStatement",
                "start": 216,
                "end": 312,
                "loc": {
                  "start": {
                    "line": 6,
                    "column": 39
                  },
                  "end": {
                    "line": 8,
                    "column": 3
                  }
                },
                "body": [
                  {
                    "type": "ExpressionStatement",
                    "start": 280,
                    "end": 308,
                    "loc": {
                      "start": {
                        "line": 7,
                        "column": 2
                      },
                      "end": {
                        "line": 7,
                        "column": 30
                      }
                    },
                    "expression": {
                      "type": "AssignmentExpression",
                      "start": 280,
                      "end": 307,
                      "loc": {
                        "start": {
                          "line": 7,
                          "column": 2
                        },
                        "end": {
                          "line": 7,
                          "column": 29
                        }
                      },
                      "operator": "=",
                      "left": {
                        "type": "Identifier",
                        "start": 280,
                        "end": 287,
                        "loc": {
                          "start": {
                            "line": 7,
                            "column": 2
                          },
                          "end": {
                            "line": 7,
                            "column": 9
                          },
                          "identifierName": "reverse"
                        },
                        "name": "reverse",
                        "leadingComments": null
                      },
                      "right": {
                        "type": "BinaryExpression",
                        "start": 290,
                        "end": 307,
                        "loc": {
                          "start": {
                            "line": 7,
                            "column": 12
                          },
                          "end": {
                            "line": 7,
                            "column": 29
                          }
                        },
                        "left": {
                          "type": "Identifier",
                          "start": 290,
                          "end": 297,
                          "loc": {
                            "start": {
                              "line": 7,
                              "column": 12
                            },
                            "end": {
                              "line": 7,
                              "column": 19
                            },
                            "identifierName": "reverse"
                          },
                          "name": "reverse"
                        },
                        "operator": "+",
                        "right": {
                          "type": "MemberExpression",
                          "start": 300,
                          "end": 307,
                          "loc": {
                            "start": {
                              "line": 7,
                              "column": 22
                            },
                            "end": {
                              "line": 7,
                              "column": 29
                            }
                          },
                          "object": {
                            "type": "Identifier",
                            "start": 300,
                            "end": 304,
                            "loc": {
                              "start": {
                                "line": 7,
                                "column": 22
                              },
                              "end": {
                                "line": 7,
                                "column": 26
                              },
                              "identifierName": "data"
                            },
                            "name": "data"
                          },
                          "property": {
                            "type": "Identifier",
                            "start": 305,
                            "end": 306,
                            "loc": {
                              "start": {
                                "line": 7,
                                "column": 27
                              },
                              "end": {
                                "line": 7,
                                "column": 28
                              },
                              "identifierName": "i"
                            },
                            "name": "i"
                          },
                          "computed": true
                        }
                      },
                      "leadingComments": null
                    },
                    "leadingComments": [
                      {
                        "type": "CommentLine",
                        "value": " decrement back so that the words come in reverse order",
                        "start": 220,
                        "end": 277,
                        "loc": {
                          "start": {
                            "line": 6,
                            "column": 43
                          },
                          "end": {
                            "line": 6,
                            "column": 100
                          }
                        }
                      }
                    ]
                  }
                ],
                "directives": [],
                "trailingComments": null
              },
              "trailingComments": [
                {
                  "type": "CommentBlock",
                  "value": "*\n   * @return {number} this is description.\n   ",
                  "start": 315,
                  "end": 367,
                  "loc": {
                    "start": {
                      "line": 9,
                      "column": 2
                    },
                    "end": {
                      "line": 11,
                      "column": 5
                    }
                  }
                }
              ]
            },
            {
              "type": "ReturnStatement",
              "start": 370,
              "end": 385,
              "loc": {
                "start": {
                  "line": 12,
                  "column": 2
                },
                "end": {
                  "line": 12,
                  "column": 17
                }
              },
              "argument": {
                "type": "Identifier",
                "start": 377,
                "end": 384,
                "loc": {
                  "start": {
                    "line": 12,
                    "column": 9
                  },
                  "end": {
                    "line": 12,
                    "column": 16
                  },
                  "identifierName": "reverse"
                },
                "name": "reverse",
                "leadingComments": null
              },
              "leadingComments": [
                {
                  "type": "CommentBlock",
                  "value": "*\n   * @return {number} this is description.\n   ",
                  "start": 315,
                  "end": 367,
                  "loc": {
                    "start": {
                      "line": 9,
                      "column": 2
                    },
                    "end": {
                      "line": 11,
                      "column": 5
                    }
                  }
                }
              ]
            }
          ],
          "directives": []
        },
        "leadingComments": [
          {
            "type": "CommentBlock",
            "value": "* Reversing a String Using looping\n * @param {function(foo: number, bar: string): boolean} param - this is function param.\n ",
            "start": 0,
            "end": 128,
            "loc": {
              "start": {
                "line": 1,
                "column": 0
              },
              "end": {
                "line": 3,
                "column": 3
              }
            }
          }
        ]
      },
      {
        "type": "ExpressionStatement",
        "start": 389,
        "end": 422,
        "loc": {
          "start": {
            "line": 15,
            "column": 0
          },
          "end": {
            "line": 15,
            "column": 33
          }
        },
        "expression": {
          "type": "CallExpression",
          "start": 389,
          "end": 421,
          "loc": {
            "start": {
              "line": 15,
              "column": 0
            },
            "end": {
              "line": 15,
              "column": 32
            }
          },
          "callee": {
            "type": "Identifier",
            "start": 389,
            "end": 402,
            "loc": {
              "start": {
                "line": 15,
                "column": 0
              },
              "end": {
                "line": 15,
                "column": 13
              },
              "identifierName": "StringReverse"
            },
            "name": "StringReverse"
          },
          "arguments": [
            {
              "type": "StringLiteral",
              "start": 403,
              "end": 420,
              "loc": {
                "start": {
                  "line": 15,
                  "column": 14
                },
                "end": {
                  "line": 15,
                  "column": 31
                }
              },
              "extra": {
                "rawValue": "HARSHIT_MANDADA",
                "raw": "\"HARSHIT_MANDADA\""
              },
              "value": "HARSHIT_MANDADA"
            }
          ]
        }
      }
    ],
    "directives": []
  },
  "comments": [
    {
      "type": "CommentBlock",
      "value": "* Reversing a String Using looping\n * @param {function(foo: number, bar: string): boolean} param - this is function param.\n ",
      "start": 0,
      "end": 128,
      "loc": {
        "start": {
          "line": 1,
          "column": 0
        },
        "end": {
          "line": 3,
          "column": 3
        }
      }
    },
    {
      "type": "CommentLine",
      "value": " decrement back so that the words come in reverse order",
      "start": 220,
      "end": 277,
      "loc": {
        "start": {
          "line": 6,
          "column": 43
        },
        "end": {
          "line": 6,
          "column": 100
        }
      }
    },
    {
      "type": "CommentBlock",
      "value": "*\n   * @return {number} this is description.\n   ",
      "start": 315,
      "end": 367,
      "loc": {
        "start": {
          "line": 9,
          "column": 2
        },
        "end": {
          "line": 11,
          "column": 5
        }
      }
    }
  ],
  "tokens": [
    {
      "type": "CommentBlock",
      "value": "* Reversing a String Using looping\n * @param {function(foo: number, bar: string): boolean} param - this is function param.\n ",
      "start": 0,
      "end": 128,
      "loc": {
        "start": {
          "line": 1,
          "column": 0
        },
        "end": {
          "line": 3,
          "column": 3
        }
      }
    },
    {
      "type": {
        "label": "function",
        "keyword": "function",
        "beforeExpr": false,
        "startsExpr": true,
        "rightAssociative": false,
        "isLoop": false,
        "isAssign": false,
        "prefix": false,
        "postfix": false,
        "binop": null
      },
      "value": "function",
      "start": 129,
      "end": 137,
      "loc": {
        "start": {
          "line": 4,
          "column": 0
        },
        "end": {
          "line": 4,
          "column": 8
        }
      }
    },
    {
      "type": {
        "label": "name",
        "beforeExpr": false,
        "startsExpr": true,
        "rightAssociative": false,
        "isLoop": false,
        "isAssign": false,
        "prefix": false,
        "postfix": false,
        "binop": null
      },
      "value": "StringReverse",
      "start": 138,
      "end": 151,
      "loc": {
        "start": {
          "line": 4,
          "column": 9
        },
        "end": {
          "line": 4,
          "column": 22
        }
      }
    },
    {
      "type": {
        "label": "(",
        "beforeExpr": true,
        "startsExpr": true,
        "rightAssociative": false,
        "isLoop": false,
        "isAssign": false,
        "prefix": false,
        "postfix": false,
        "binop": null
      },
      "start": 151,
      "end": 152,
      "loc": {
        "start": {
          "line": 4,
          "column": 22
        },
        "end": {
          "line": 4,
          "column": 23
        }
      }
    },
    {
      "type": {
        "label": "name",
        "beforeExpr": false,
        "startsExpr": true,
        "rightAssociative": false,
        "isLoop": false,
        "isAssign": false,
        "prefix": false,
        "postfix": false,
        "binop": null
      },
      "value": "data",
      "start": 152,
      "end": 156,
      "loc": {
        "start": {
          "line": 4,
          "column": 23
        },
        "end": {
          "line": 4,
          "column": 27
        }
      }
    },
    {
      "type": {
        "label": ")",
        "beforeExpr": false,
        "startsExpr": false,
        "rightAssociative": false,
        "isLoop": false,
        "isAssign": false,
        "prefix": false,
        "postfix": false,
        "binop": null
      },
      "start": 156,
      "end": 157,
      "loc": {
        "start": {
          "line": 4,
          "column": 27
        },
        "end": {
          "line": 4,
          "column": 28
        }
      }
    },
    {
      "type": {
        "label": "{",
        "beforeExpr": true,
        "startsExpr": true,
        "rightAssociative": false,
        "isLoop": false,
        "isAssign": false,
        "prefix": false,
        "postfix": false,
        "binop": null
      },
      "start": 157,
      "end": 158,
      "loc": {
        "start": {
          "line": 4,
          "column": 28
        },
        "end": {
          "line": 4,
          "column": 29
        }
      }
    },
    {
      "type": {
        "label": "let",
        "keyword": "let",
        "beforeExpr": false,
        "startsExpr": false,
        "rightAssociative": false,
        "isLoop": false,
        "isAssign": false,
        "prefix": false,
        "postfix": false,
        "binop": null,
        "updateContext": null
      },
      "value": "let",
      "start": 161,
      "end": 164,
      "loc": {
        "start": {
          "line": 5,
          "column": 2
        },
        "end": {
          "line": 5,
          "column": 5
        }
      }
    },
    {
      "type": {
        "label": "name",
        "beforeExpr": false,
        "startsExpr": true,
        "rightAssociative": false,
        "isLoop": false,
        "isAssign": false,
        "prefix": false,
        "postfix": false,
        "binop": null
      },
      "value": "reverse",
      "start": 165,
      "end": 172,
      "loc": {
        "start": {
          "line": 5,
          "column": 6
        },
        "end": {
          "line": 5,
          "column": 13
        }
      }
    },
    {
      "type": {
        "label": "=",
        "beforeExpr": true,
        "startsExpr": false,
        "rightAssociative": false,
        "isLoop": false,
        "isAssign": true,
        "prefix": false,
        "postfix": false,
        "binop": null,
        "updateContext": null
      },
      "value": "=",
      "start": 172,
      "end": 173,
      "loc": {
        "start": {
          "line": 5,
          "column": 13
        },
        "end": {
          "line": 5,
          "column": 14
        }
      }
    },
    {
      "type": {
        "label": "string",
        "beforeExpr": false,
        "startsExpr": true,
        "rightAssociative": false,
        "isLoop": false,
        "isAssign": false,
        "prefix": false,
        "postfix": false,
        "binop": null,
        "updateContext": null
      },
      "value": "",
      "start": 173,
      "end": 175,
      "loc": {
        "start": {
          "line": 5,
          "column": 14
        },
        "end": {
          "line": 5,
          "column": 16
        }
      }
    },
    {
      "type": {
        "label": ";",
        "beforeExpr": true,
        "startsExpr": false,
        "rightAssociative": false,
        "isLoop": false,
        "isAssign": false,
        "prefix": false,
        "postfix": false,
        "binop": null,
        "updateContext": null
      },
      "start": 175,
      "end": 176,
      "loc": {
        "start": {
          "line": 5,
          "column": 16
        },
        "end": {
          "line": 5,
          "column": 17
        }
      }
    },
    {
      "type": {
        "label": "for",
        "keyword": "for",
        "beforeExpr": false,
        "startsExpr": false,
        "rightAssociative": false,
        "isLoop": true,
        "isAssign": false,
        "prefix": false,
        "postfix": false,
        "binop": null,
        "updateContext": null
      },
      "value": "for",
      "start": 179,
      "end": 182,
      "loc": {
        "start": {
          "line": 6,
          "column": 2
        },
        "end": {
          "line": 6,
          "column": 5
        }
      }
    },
    {
      "type": {
        "label": "(",
        "beforeExpr": true,
        "startsExpr": true,
        "rightAssociative": false,
        "isLoop": false,
        "isAssign": false,
        "prefix": false,
        "postfix": false,
        "binop": null
      },
      "start": 182,
      "end": 183,
      "loc": {
        "start": {
          "line": 6,
          "column": 5
        },
        "end": {
          "line": 6,
          "column": 6
        }
      }
    },
    {
      "type": {
        "label": "var",
        "keyword": "var",
        "beforeExpr": false,
        "startsExpr": false,
        "rightAssociative": false,
        "isLoop": false,
        "isAssign": false,
        "prefix": false,
        "postfix": false,
        "binop": null,
        "updateContext": null
      },
      "value": "var",
      "start": 183,
      "end": 186,
      "loc": {
        "start": {
          "line": 6,
          "column": 6
        },
        "end": {
          "line": 6,
          "column": 9
        }
      }
    },
    {
      "type": {
        "label": "name",
        "beforeExpr": false,
        "startsExpr": true,
        "rightAssociative": false,
        "isLoop": false,
        "isAssign": false,
        "prefix": false,
        "postfix": false,
        "binop": null
      },
      "value": "i",
      "start": 187,
      "end": 188,
      "loc": {
        "start": {
          "line": 6,
          "column": 10
        },
        "end": {
          "line": 6,
          "column": 11
        }
      }
    },
    {
      "type": {
        "label": "=",
        "beforeExpr": true,
        "startsExpr": false,
        "rightAssociative": false,
        "isLoop": false,
        "isAssign": true,
        "prefix": false,
        "postfix": false,
        "binop": null,
        "updateContext": null
      },
      "value": "=",
      "start": 189,
      "end": 190,
      "loc": {
        "start": {
          "line": 6,
          "column": 12
        },
        "end": {
          "line": 6,
          "column": 13
        }
      }
    },
    {
      "type": {
        "label": "name",
        "beforeExpr": false,
        "startsExpr": true,
        "rightAssociative": false,
        "isLoop": false,
        "isAssign": false,
        "prefix": false,
        "postfix": false,
        "binop": null
      },
      "value": "data",
      "start": 191,
      "end": 195,
      "loc": {
        "start": {
          "line": 6,
          "column": 14
        },
        "end": {
          "line": 6,
          "column": 18
        }
      }
    },
    {
      "type": {
        "label": ".",
        "beforeExpr": false,
        "startsExpr": false,
        "rightAssociative": false,
        "isLoop": false,
        "isAssign": false,
        "prefix": false,
        "postfix": false,
        "binop": null,
        "updateContext": null
      },
      "start": 195,
      "end": 196,
      "loc": {
        "start": {
          "line": 6,
          "column": 18
        },
        "end": {
          "line": 6,
          "column": 19
        }
      }
    },
    {
      "type": {
        "label": "name",
        "beforeExpr": false,
        "startsExpr": true,
        "rightAssociative": false,
        "isLoop": false,
        "isAssign": false,
        "prefix": false,
        "postfix": false,
        "binop": null
      },
      "value": "length",
      "start": 196,
      "end": 202,
      "loc": {
        "start": {
          "line": 6,
          "column": 19
        },
        "end": {
          "line": 6,
          "column": 25
        }
      }
    },
    {
      "type": {
        "label": "+/-",
        "beforeExpr": true,
        "startsExpr": true,
        "rightAssociative": false,
        "isLoop": false,
        "isAssign": false,
        "prefix": true,
        "postfix": false,
        "binop": 9,
        "updateContext": null
      },
      "value": "-",
      "start": 202,
      "end": 203,
      "loc": {
        "start": {
          "line": 6,
          "column": 25
        },
        "end": {
          "line": 6,
          "column": 26
        }
      }
    },
    {
      "type": {
        "label": "num",
        "beforeExpr": false,
        "startsExpr": true,
        "rightAssociative": false,
        "isLoop": false,
        "isAssign": false,
        "prefix": false,
        "postfix": false,
        "binop": null,
        "updateContext": null
      },
      "value": 1,
      "start": 203,
      "end": 204,
      "loc": {
        "start": {
          "line": 6,
          "column": 26
        },
        "end": {
          "line": 6,
          "column": 27
        }
      }
    },
    {
      "type": {
        "label": ";",
        "beforeExpr": true,
        "startsExpr": false,
        "rightAssociative": false,
        "isLoop": false,
        "isAssign": false,
        "prefix": false,
        "postfix": false,
        "binop": null,
        "updateContext": null
      },
      "start": 204,
      "end": 205,
      "loc": {
        "start": {
          "line": 6,
          "column": 27
        },
        "end": {
          "line": 6,
          "column": 28
        }
      }
    },
    {
      "type": {
        "label": "name",
        "beforeExpr": false,
        "startsExpr": true,
        "rightAssociative": false,
        "isLoop": false,
        "isAssign": false,
        "prefix": false,
        "postfix": false,
        "binop": null
      },
      "value": "i",
      "start": 206,
      "end": 207,
      "loc": {
        "start": {
          "line": 6,
          "column": 29
        },
        "end": {
          "line": 6,
          "column": 30
        }
      }
    },
    {
      "type": {
        "label": "</>",
        "beforeExpr": true,
        "startsExpr": false,
        "rightAssociative": false,
        "isLoop": false,
        "isAssign": false,
        "prefix": false,
        "postfix": false,
        "binop": 7,
        "updateContext": null
      },
      "value": ">=",
      "start": 207,
      "end": 209,
      "loc": {
        "start": {
          "line": 6,
          "column": 30
        },
        "end": {
          "line": 6,
          "column": 32
        }
      }
    },
    {
      "type": {
        "label": "num",
        "beforeExpr": false,
        "startsExpr": true,
        "rightAssociative": false,
        "isLoop": false,
        "isAssign": false,
        "prefix": false,
        "postfix": false,
        "binop": null,
        "updateContext": null
      },
      "value": 0,
      "start": 209,
      "end": 210,
      "loc": {
        "start": {
          "line": 6,
          "column": 32
        },
        "end": {
          "line": 6,
          "column": 33
        }
      }
    },
    {
      "type": {
        "label": ";",
        "beforeExpr": true,
        "startsExpr": false,
        "rightAssociative": false,
        "isLoop": false,
        "isAssign": false,
        "prefix": false,
        "postfix": false,
        "binop": null,
        "updateContext": null
      },
      "start": 210,
      "end": 211,
      "loc": {
        "start": {
          "line": 6,
          "column": 33
        },
        "end": {
          "line": 6,
          "column": 34
        }
      }
    },
    {
      "type": {
        "label": "name",
        "beforeExpr": false,
        "startsExpr": true,
        "rightAssociative": false,
        "isLoop": false,
        "isAssign": false,
        "prefix": false,
        "postfix": false,
        "binop": null
      },
      "value": "i",
      "start": 212,
      "end": 213,
      "loc": {
        "start": {
          "line": 6,
          "column": 35
        },
        "end": {
          "line": 6,
          "column": 36
        }
      }
    },
    {
      "type": {
        "label": "++/--",
        "beforeExpr": false,
        "startsExpr": true,
        "rightAssociative": false,
        "isLoop": false,
        "isAssign": false,
        "prefix": true,
        "postfix": true,
        "binop": null
      },
      "value": "--",
      "start": 213,
      "end": 215,
      "loc": {
        "start": {
          "line": 6,
          "column": 36
        },
        "end": {
          "line": 6,
          "column": 38
        }
      }
    },
    {
      "type": {
        "label": ")",
        "beforeExpr": false,
        "startsExpr": false,
        "rightAssociative": false,
        "isLoop": false,
        "isAssign": false,
        "prefix": false,
        "postfix": false,
        "binop": null
      },
      "start": 215,
      "end": 216,
      "loc": {
        "start": {
          "line": 6,
          "column": 38
        },
        "end": {
          "line": 6,
          "column": 39
        }
      }
    },
    {
      "type": {
        "label": "{",
        "beforeExpr": true,
        "startsExpr": true,
        "rightAssociative": false,
        "isLoop": false,
        "isAssign": false,
        "prefix": false,
        "postfix": false,
        "binop": null
      },
      "start": 216,
      "end": 217,
      "loc": {
        "start": {
          "line": 6,
          "column": 39
        },
        "end": {
          "line": 6,
          "column": 40
        }
      }
    },
    {
      "type": "CommentLine",
      "value": " decrement back so that the words come in reverse order",
      "start": 220,
      "end": 277,
      "loc": {
        "start": {
          "line": 6,
          "column": 43
        },
        "end": {
          "line": 6,
          "column": 100
        }
      }
    },
    {
      "type": {
        "label": "name",
        "beforeExpr": false,
        "startsExpr": true,
        "rightAssociative": false,
        "isLoop": false,
        "isAssign": false,
        "prefix": false,
        "postfix": false,
        "binop": null
      },
      "value": "reverse",
      "start": 280,
      "end": 287,
      "loc": {
        "start": {
          "line": 7,
          "column": 2
        },
        "end": {
          "line": 7,
          "column": 9
        }
      }
    },
    {
      "type": {
        "label": "=",
        "beforeExpr": true,
        "startsExpr": false,
        "rightAssociative": false,
        "isLoop": false,
        "isAssign": true,
        "prefix": false,
        "postfix": false,
        "binop": null,
        "updateContext": null
      },
      "value": "=",
      "start": 288,
      "end": 289,
      "loc": {
        "start": {
          "line": 7,
          "column": 10
        },
        "end": {
          "line": 7,
          "column": 11
        }
      }
    },
    {
      "type": {
        "label": "name",
        "beforeExpr": false,
        "startsExpr": true,
        "rightAssociative": false,
        "isLoop": false,
        "isAssign": false,
        "prefix": false,
        "postfix": false,
        "binop": null
      },
      "value": "reverse",
      "start": 290,
      "end": 297,
      "loc": {
        "start": {
          "line": 7,
          "column": 12
        },
        "end": {
          "line": 7,
          "column": 19
        }
      }
    },
    {
      "type": {
        "label": "+/-",
        "beforeExpr": true,
        "startsExpr": true,
        "rightAssociative": false,
        "isLoop": false,
        "isAssign": false,
        "prefix": true,
        "postfix": false,
        "binop": 9,
        "updateContext": null
      },
      "value": "+",
      "start": 298,
      "end": 299,
      "loc": {
        "start": {
          "line": 7,
          "column": 20
        },
        "end": {
          "line": 7,
          "column": 21
        }
      }
    },
    {
      "type": {
        "label": "name",
        "beforeExpr": false,
        "startsExpr": true,
        "rightAssociative": false,
        "isLoop": false,
        "isAssign": false,
        "prefix": false,
        "postfix": false,
        "binop": null
      },
      "value": "data",
      "start": 300,
      "end": 304,
      "loc": {
        "start": {
          "line": 7,
          "column": 22
        },
        "end": {
          "line": 7,
          "column": 26
        }
      }
    },
    {
      "type": {
        "label": "[",
        "beforeExpr": true,
        "startsExpr": true,
        "rightAssociative": false,
        "isLoop": false,
        "isAssign": false,
        "prefix": false,
        "postfix": false,
        "binop": null,
        "updateContext": null
      },
      "start": 304,
      "end": 305,
      "loc": {
        "start": {
          "line": 7,
          "column": 26
        },
        "end": {
          "line": 7,
          "column": 27
        }
      }
    },
    {
      "type": {
        "label": "name",
        "beforeExpr": false,
        "startsExpr": true,
        "rightAssociative": false,
        "isLoop": false,
        "isAssign": false,
        "prefix": false,
        "postfix": false,
        "binop": null
      },
      "value": "i",
      "start": 305,
      "end": 306,
      "loc": {
        "start": {
          "line": 7,
          "column": 27
        },
        "end": {
          "line": 7,
          "column": 28
        }
      }
    },
    {
      "type": {
        "label": "]",
        "beforeExpr": false,
        "startsExpr": false,
        "rightAssociative": false,
        "isLoop": false,
        "isAssign": false,
        "prefix": false,
        "postfix": false,
        "binop": null,
        "updateContext": null
      },
      "start": 306,
      "end": 307,
      "loc": {
        "start": {
          "line": 7,
          "column": 28
        },
        "end": {
          "line": 7,
          "column": 29
        }
      }
    },
    {
      "type": {
        "label": ";",
        "beforeExpr": true,
        "startsExpr": false,
        "rightAssociative": false,
        "isLoop": false,
        "isAssign": false,
        "prefix": false,
        "postfix": false,
        "binop": null,
        "updateContext": null
      },
      "start": 307,
      "end": 308,
      "loc": {
        "start": {
          "line": 7,
          "column": 29
        },
        "end": {
          "line": 7,
          "column": 30
        }
      }
    },
    {
      "type": {
        "label": "}",
        "beforeExpr": false,
        "startsExpr": false,
        "rightAssociative": false,
        "isLoop": false,
        "isAssign": false,
        "prefix": false,
        "postfix": false,
        "binop": null
      },
      "start": 311,
      "end": 312,
      "loc": {
        "start": {
          "line": 8,
          "column": 2
        },
        "end": {
          "line": 8,
          "column": 3
        }
      }
    },
    {
      "type": "CommentBlock",
      "value": "*\n   * @return {number} this is description.\n   ",
      "start": 315,
      "end": 367,
      "loc": {
        "start": {
          "line": 9,
          "column": 2
        },
        "end": {
          "line": 11,
          "column": 5
        }
      }
    },
    {
      "type": {
        "label": "return",
        "keyword": "return",
        "beforeExpr": true,
        "startsExpr": false,
        "rightAssociative": false,
        "isLoop": false,
        "isAssign": false,
        "prefix": false,
        "postfix": false,
        "binop": null,
        "updateContext": null
      },
      "value": "return",
      "start": 370,
      "end": 376,
      "loc": {
        "start": {
          "line": 12,
          "column": 2
        },
        "end": {
          "line": 12,
          "column": 8
        }
      }
    },
    {
      "type": {
        "label": "name",
        "beforeExpr": false,
        "startsExpr": true,
        "rightAssociative": false,
        "isLoop": false,
        "isAssign": false,
        "prefix": false,
        "postfix": false,
        "binop": null
      },
      "value": "reverse",
      "start": 377,
      "end": 384,
      "loc": {
        "start": {
          "line": 12,
          "column": 9
        },
        "end": {
          "line": 12,
          "column": 16
        }
      }
    },
    {
      "type": {
        "label": ";",
        "beforeExpr": true,
        "startsExpr": false,
        "rightAssociative": false,
        "isLoop": false,
        "isAssign": false,
        "prefix": false,
        "postfix": false,
        "binop": null,
        "updateContext": null
      },
      "start": 384,
      "end": 385,
      "loc": {
        "start": {
          "line": 12,
          "column": 16
        },
        "end": {
          "line": 12,
          "column": 17
        }
      }
    },
    {
      "type": {
        "label": "}",
        "beforeExpr": false,
        "startsExpr": false,
        "rightAssociative": false,
        "isLoop": false,
        "isAssign": false,
        "prefix": false,
        "postfix": false,
        "binop": null
      },
      "start": 386,
      "end": 387,
      "loc": {
        "start": {
          "line": 13,
          "column": 0
        },
        "end": {
          "line": 13,
          "column": 1
        }
      }
    },
    {
      "type": {
        "label": "name",
        "beforeExpr": false,
        "startsExpr": true,
        "rightAssociative": false,
        "isLoop": false,
        "isAssign": false,
        "prefix": false,
        "postfix": false,
        "binop": null
      },
      "value": "StringReverse",
      "start": 389,
      "end": 402,
      "loc": {
        "start": {
          "line": 15,
          "column": 0
        },
        "end": {
          "line": 15,
          "column": 13
        }
      }
    },
    {
      "type": {
        "label": "(",
        "beforeExpr": true,
        "startsExpr": true,
        "rightAssociative": false,
        "isLoop": false,
        "isAssign": false,
        "prefix": false,
        "postfix": false,
        "binop": null
      },
      "start": 402,
      "end": 403,
      "loc": {
        "start": {
          "line": 15,
          "column": 13
        },
        "end": {
          "line": 15,
          "column": 14
        }
      }
    },
    {
      "type": {
        "label": "string",
        "beforeExpr": false,
        "startsExpr": true,
        "rightAssociative": false,
        "isLoop": false,
        "isAssign": false,
        "prefix": false,
        "postfix": false,
        "binop": null,
        "updateContext": null
      },
      "value": "HARSHIT_MANDADA",
      "start": 403,
      "end": 420,
      "loc": {
        "start": {
          "line": 15,
          "column": 14
        },
        "end": {
          "line": 15,
          "column": 31
        }
      }
    },
    {
      "type": {
        "label": ")",
        "beforeExpr": false,
        "startsExpr": false,
        "rightAssociative": false,
        "isLoop": false,
        "isAssign": false,
        "prefix": false,
        "postfix": false,
        "binop": null
      },
      "start": 420,
      "end": 421,
      "loc": {
        "start": {
          "line": 15,
          "column": 31
        },
        "end": {
          "line": 15,
          "column": 32
        }
      }
    },
    {
      "type": {
        "label": ";",
        "beforeExpr": true,
        "startsExpr": false,
        "rightAssociative": false,
        "isLoop": false,
        "isAssign": false,
        "prefix": false,
        "postfix": false,
        "binop": null,
        "updateContext": null
      },
      "start": 421,
      "end": 422,
      "loc": {
        "start": {
          "line": 15,
          "column": 32
        },
        "end": {
          "line": 15,
          "column": 33
        }
      }
    },
    {
      "type": {
        "label": "eof",
        "beforeExpr": false,
        "startsExpr": false,
        "rightAssociative": false,
        "isLoop": false,
        "isAssign": false,
        "prefix": false,
        "postfix": false,
        "binop": null,
        "updateContext": null
      },
      "start": 422,
      "end": 422,
      "loc": {
        "start": {
          "line": 15,
          "column": 33
        },
        "end": {
          "line": 15,
          "column": 33
        }
      }
    }
  ]
}